riogisoffline/LICENSE
riogisoffline/Makefile
riogisoffline/README.md
riogisoffline/__init__.py
riogisoffline/compile.bat
riogisoffline/icon.png
riogisoffline/metadata.txt
riogisoffline/pb_tool.cfg
riogisoffline/plugin_upload.py
riogisoffline/pylintrc
riogisoffline/requirements.txt
riogisoffline/resources.qrc
riogisoffline/settings.json
riogisoffline/dialog/riogis_dialog_change_project_status.ui
riogisoffline/dialog/riogis_dialog_change_status.ui
riogisoffline/dialog/riogis_dialog_export.ui
riogisoffline/dialog/riogis_dialog_settings.ui
riogisoffline/dialog/riogis_dialog_upload.ui
riogisoffline/dialog/riogis_dockwidget.ui
riogisoffline/plugin/__init__.py
riogisoffline/plugin/azure_blob_storage_connection.py
riogisoffline/plugin/change_project_status_dialog.py
riogisoffline/plugin/change_status_dialog.py
riogisoffline/plugin/dependency_installer.py
riogisoffline/plugin/export_dialog.py
riogisoffline/plugin/multi_thread_job.py
riogisoffline/plugin/refresh_map.py
riogisoffline/plugin/resources.py
riogisoffline/plugin/riogis.py
riogisoffline/plugin/riogis_dockedwidget.py
riogisoffline/plugin/search_box.py
riogisoffline/plugin/settings_dialog.py
riogisoffline/plugin/syncronizer.py
riogisoffline/plugin/upload_dialog.py
riogisoffline/plugin/user_settings_generator.py
riogisoffline/plugin/utils.py
riogisoffline/plugin/worker.py
riogisoffline-0.5.3.dist-info/licenses/riogisoffline/LICENSE
riogisoffline-0.5.3.dist-info/WHEEL
riogisoffline-0.5.3.dist-info/METADATA
riogisoffline-0.5.3.dist-info/RECORD
