Metadata-Version: 2.4
Name: riogisoffline
Version: 0.5.3
Summary: This Exports attributes of a given feature to a Wincan consumable text file.
Author-email: Vann- og avløpsetaten Oslo kommune <gis@vav.oslo.kommune.no>
Requires-Python: >=3.7
Classifier: Programming Language :: Python :: 3
Classifier: License :: OSI Approved :: MIT License
Classifier: Operating System :: OS Independent
License-File: riogisoffline/LICENSE
Project-URL: Homepage, https://github.com/vavpp/riogisoffline
Project-URL: Issues, https://github.com/vavpp/riogisoffline/issues
